mqt/debugger/__init__.py
mqt/debugger/_version.py
mqt/debugger/_version.pyi
mqt/debugger/py.typed
mqt/debugger/pydebugger.cpython-314-aarch64-linux-gnu.so
mqt/debugger/pydebugger.pyi
mqt/debugger/check/__init__.py
mqt/debugger/check/__main__.py
mqt/debugger/check/calibration.py
mqt/debugger/check/result_checker.py
mqt/debugger/check/run_preparation.py
mqt/debugger/check/runtime_check.py
mqt/debugger/dap/__init__.py
mqt/debugger/dap/adapter.py
mqt/debugger/dap/dap_server.py
mqt/debugger/dap/messages/__init__.py
mqt/debugger/dap/messages/capabilities_dap_event.py
mqt/debugger/dap/messages/configuration_done_dap_message.py
mqt/debugger/dap/messages/continue_dap_message.py
mqt/debugger/dap/messages/dap_event.py
mqt/debugger/dap/messages/dap_message.py
mqt/debugger/dap/messages/disconnect_dap_message.py
mqt/debugger/dap/messages/exception_info_message.py
mqt/debugger/dap/messages/exited_dap_event.py
mqt/debugger/dap/messages/gray_out_event.py
mqt/debugger/dap/messages/initialize_dap_message.py
mqt/debugger/dap/messages/initialized_dap_event.py
mqt/debugger/dap/messages/launch_dap_message.py
mqt/debugger/dap/messages/next_dap_message.py
mqt/debugger/dap/messages/output_dap_event.py
mqt/debugger/dap/messages/pause_dap_message.py
mqt/debugger/dap/messages/restart_dap_message.py
mqt/debugger/dap/messages/restart_frame_dap_message.py
mqt/debugger/dap/messages/reverse_continue_dap_message.py
mqt/debugger/dap/messages/scopes_dap_message.py
mqt/debugger/dap/messages/set_breakpoints_dap_message.py
mqt/debugger/dap/messages/set_exception_breakpoints_dap_message.py
mqt/debugger/dap/messages/stack_trace_dap_message.py
mqt/debugger/dap/messages/step_back_dap_message.py
mqt/debugger/dap/messages/step_in_dap_message.py
mqt/debugger/dap/messages/step_out_dap_message.py
mqt/debugger/dap/messages/stopped_dap_event.py
mqt/debugger/dap/messages/terminate_dap_message.py
mqt/debugger/dap/messages/terminated_dap_event.py
mqt_debugger-1.2.0.dist-info/METADATA
mqt_debugger-1.2.0.dist-info/WHEEL
mqt_debugger-1.2.0.dist-info/entry_points.txt
mqt_debugger-1.2.0.dist-info/RECORD
mqt_debugger-1.2.0.dist-info/licenses/LICENSE.md
