Metadata-Version: 2.4
Name: mqt-debugger
Version: 1.2.0
Summary: A quantum circuit debugging tool
Keywords: MQT,quantum-computing,design-automation,verification,debugging,dap
Author-Email: Damian Rovara <damian.rovara@tum.de>, Lukas Burgholzer <burgholzer@me.com>
License-Expression: MIT
License-File: LICENSE.md
Classifier: Development Status :: 5 - Production/Stable
Classifier: Intended Audience :: Science/Research
Classifier: Natural Language :: English
Classifier: Operating System :: MacOS
Classifier: Operating System :: Microsoft :: Windows
Classifier: Operating System :: POSIX :: Linux
Classifier: Programming Language :: C++
Classifier: Programming Language :: Python
Classifier: Programming Language :: Python :: 3 :: Only
Classifier: Programming Language :: Python :: 3.10
Classifier: Programming Language :: Python :: 3.11
Classifier: Programming Language :: Python :: 3.12
Classifier: Programming Language :: Python :: 3.13
Classifier: Programming Language :: Python :: 3.14
Classifier: Topic :: Scientific/Engineering :: Electronic Design Automation (EDA)
Classifier: Typing :: Typed
Project-URL: Homepage, https://github.com/munich-quantum-toolkit/debugger
Project-URL: Documentation, https://mqt.readthedocs.io/projects/debugger
Project-URL: Issues, https://github.com/munich-quantum-toolkit/debugger/issues
Project-URL: Discussions, https://github.com/munich-quantum-toolkit/debugger/discussions
Requires-Python: >=3.10
Provides-Extra: check
Requires-Dist: qiskit>=1.2.4; extra == "check"
Requires-Dist: scipy>=1.13.1; python_version < "3.13" and extra == "check"
Requires-Dist: scipy>=1.15; python_version >= "3.13" and extra == "check"
Requires-Dist: scipy>=1.16.2; python_version >= "3.14" and extra == "check"
Requires-Dist: numpy>=2.1; python_version >= "3.13" and extra == "check"
Requires-Dist: numpy>=2.3.2; python_version >= "3.14" and extra == "check"
